lib_regexp/__init__.py
lib_regexp/lib_regexp.py
lib_regexp/version.txt
lib_regexp-0.0.1.dist-info/LICENSE
lib_regexp-0.0.1.dist-info/METADATA
lib_regexp-0.0.1.dist-info/WHEEL
lib_regexp-0.0.1.dist-info/top_level.txt
lib_regexp-0.0.1.dist-info/RECORD
