Metadata-Version: 2.1
Name: lib-regexp
Version: 0.0.1
Summary: lib_regexp
Home-page: https://github.com/bitranox/lib_regexp
Author: Robert Nowotny
Author-email: rnowotny1966@gmail.com
License: UNKNOWN
Platform: UNKNOWN
Classifier: Development Status :: 5 - Production/Stable
Classifier: Intended Audience :: Developers
Classifier: License :: OSI Approved :: MIT License
Classifier: Natural Language :: English
Classifier: Operating System :: OS Independent
Classifier: Programming Language :: Python
Classifier: Topic :: Software Development :: Libraries :: Python Modules
Requires-Dist: typing
Requires-Dist: pathlib
